COPYING
MANIFEST.in
README.rst
bootstrap.py
buildout.cfg
setup.py
xbob/__init__.py
xbob.db.utfvp.egg-info/PKG-INFO
xbob.db.utfvp.egg-info/SOURCES.txt
xbob.db.utfvp.egg-info/dependency_links.txt
xbob.db.utfvp.egg-info/entry_points.txt
xbob.db.utfvp.egg-info/namespace_packages.txt
xbob.db.utfvp.egg-info/not-zip-safe
xbob.db.utfvp.egg-info/requires.txt
xbob.db.utfvp.egg-info/top_level.txt
xbob/db/__init__.py
xbob/db/utfvp/__init__.py
xbob/db/utfvp/create.py
xbob/db/utfvp/db.sql3
xbob/db/utfvp/driver.py
xbob/db/utfvp/models.py
xbob/db/utfvp/query.py
xbob/db/utfvp/test.py