Metadata-Version: 1.1
Name: xbob.db.utfvp
Version: 2.0.0
Summary: UTFVP Database Access API for Bob
Home-page: https://github.com/bioidiap/xbob.db.utfvp.git
Author: Pedro Tome
Author-email: pedro.tome@idiap.ch
License: GPLv3
Keywords: vein recognition,bob,xbob,xbob.db,UTFVP
Platform: UNKNOWN
Classifier: Development Status :: 4 - Beta
Classifier: Environment :: Console
Classifier: Intended Audience :: Developers
Classifier: Intended Audience :: Education
Classifier: Intended Audience :: Science/Research
Classifier: License :: OSI Approved :: GNU General Public License v3 (GPLv3)
Classifier: Natural Language :: English
Classifier: Programming Language :: Python
Classifier: Programming Language :: Python :: 3
Classifier: Topic :: Scientific/Engineering :: Artificial Intelligence
Classifier: Topic :: Database :: Front-Ends
